crossix/__init__.py
crossix/settings.py
crossix/urls.py
crossix/wsgi.py
crossix/assets/staticfiles.json
crossix/assets/admin/css/autocomplete.781713f30664.css
crossix/assets/admin/css/autocomplete.css
crossix/assets/admin/css/base.css
crossix/assets/admin/css/base.efb520c4bb7c.css
crossix/assets/admin/css/changelists.09730d6ad169.css
crossix/assets/admin/css/changelists.css
crossix/assets/admin/css/dashboard.be83f13e4369.css
crossix/assets/admin/css/dashboard.css
crossix/assets/admin/css/fonts.168bab448fee.css
crossix/assets/admin/css/fonts.css
crossix/assets/admin/css/forms.6230fc2a74ac.css
crossix/assets/admin/css/forms.css
crossix/assets/admin/css/login.css
crossix/assets/admin/css/login.d2a477e04949.css
crossix/assets/admin/css/nav_sidebar.59831780a474.css
crossix/assets/admin/css/nav_sidebar.css
crossix/assets/admin/css/responsive.5a9bb635f4d5.css
crossix/assets/admin/css/responsive.css
crossix/assets/admin/css/responsive_rtl.css
crossix/assets/admin/css/responsive_rtl.e13ae754cceb.css
crossix/assets/admin/css/rtl.775b89eb85cb.css
crossix/assets/admin/css/rtl.css
crossix/assets/admin/css/widgets.b12c020d05e0.css
crossix/assets/admin/css/widgets.css
crossix/assets/admin/css/vendor/select2/LICENSE-SELECT2.f94142512c91.md
crossix/assets/admin/css/vendor/select2/LICENSE-SELECT2.md
crossix/assets/admin/css/vendor/select2/select2.a2194c262648.css
crossix/assets/admin/css/vendor/select2/select2.css
crossix/assets/admin/css/vendor/select2/select2.min.9f54e6414f87.css
crossix/assets/admin/css/vendor/select2/select2.min.css
crossix/assets/admin/fonts/LICENSE.d273d63619c9.txt
crossix/assets/admin/fonts/LICENSE.txt
crossix/assets/admin/fonts/README.ab99e6b541ea.txt
crossix/assets/admin/fonts/README.txt
crossix/assets/admin/fonts/Roboto-Bold-webfont.50d75e48e0a3.woff
crossix/assets/admin/fonts/Roboto-Bold-webfont.woff
crossix/assets/admin/fonts/Roboto-Light-webfont.c73eb1ceba33.woff
crossix/assets/admin/fonts/Roboto-Light-webfont.woff
crossix-2021.0.0.dist-info/LICENSE
crossix-2021.0.0.dist-info/METADATA
crossix-2021.0.0.dist-info/WHEEL
crossix-2021.0.0.dist-info/top_level.txt
crossix-2021.0.0.dist-info/RECORD
