Metadata-Version: 2.1
Name: crossix
Version: 2021.0.0
Summary: Simple website for Cross triangulaire registration.
Home-page: https://git.xelnor.net/crossix/
Author: Raphaël Barrois
Author-email: raphael.barrois+crossix@polytechnique.org
License: MIT
Keywords: crossix
Platform: UNKNOWN
Classifier: Development Status :: 5 - Production/Stable
Classifier: Environment :: Web Environment
Classifier: Framework :: Django
Classifier: Intended Audience :: Developers
Classifier: License :: OSI Approved :: MIT License
Classifier: Operating System :: OS Independent
Classifier: Programming Language :: Python
Classifier: Programming Language :: Python :: 3.6
Classifier: Programming Language :: Python :: 3.7
Classifier: Programming Language :: Python :: 3.8
Requires-Dist: Django (>=3.1)
Requires-Dist: django-sendfile2 (>=0.6.0)
Requires-Dist: getconf (>=1.3.0)
Requires-Dist: markdown
